build_a_brain/__init__.py
build_a_brain/interface.py
build_a_brain/neural_classes.py
build_a_brain/neural_simulator.py
build_a_brain-1.0.1.dist-info/METADATA
build_a_brain-1.0.1.dist-info/WHEEL
build_a_brain-1.0.1.dist-info/top_level.txt
build_a_brain-1.0.1.dist-info/RECORD
