Metadata-Version: 2.1
Name: build_a_brain
Version: 1.0.1
Summary: Builds a LIF neural network
Author-email: Noah Stanis <stani123@uw.edu>
Classifier: Programming Language :: Python :: 3
Classifier: License :: OSI Approved :: MIT License
Classifier: Operating System :: OS Independent
Requires-Python: >=3.11
Requires-Dist: numpy>=1.26.4
Requires-Dist: matplotlib>=3.8.3
Requires-Dist: tk>=0.1.0
